setup.py
RasaWS.egg-info/PKG-INFO
RasaWS.egg-info/SOURCES.txt
RasaWS.egg-info/dependency_links.txt
RasaWS.egg-info/requires.txt
RasaWS.egg-info/top_level.txt
RasaWSHH/__init__.py
RasaWSHH/__main__.py
RasaWSHH/constants.py
RasaWSHH/data.py
RasaWSHH/exceptions.py
RasaWSHH/jupyter.py
RasaWSHH/model.py
RasaWSHH/run.py
RasaWSHH/server.py
RasaWSHH/test.py
RasaWSHH/train.py
RasaWSHH/validator.py
RasaWSHH/version.py