Metadata-Version: 1.0
Name: RasaWS
Version: 1.0.2
Summary: 文思海辉基于Rasa的多轮对话安装包
Home-page: https://pypi.org
Author: bradzuo
Author-email: 289126709@qq.com
License: UNKNOWN
Platform: UNKNOWN
